scuec_auth/__init__.py
scuec_auth/_compat.py
scuec_auth/auth.py
scuec_auth/session.py
scuec_auth/utils.py
SCUECAuth-1.1.4.dist-info/LICENSE
SCUECAuth-1.1.4.dist-info/METADATA
SCUECAuth-1.1.4.dist-info/WHEEL
SCUECAuth-1.1.4.dist-info/top_level.txt
SCUECAuth-1.1.4.dist-info/RECORD
