Metadata-Version: 2.1
Name: SCUECAuth
Version: 1.1.4
Summary: The authentication module of SCUEC.
Home-page: https://github.com/WengChaoxi/scuec-auth
Author: WengChaoxi
Author-email: 352120190@qq.com
License: MIT
Platform: UNKNOWN
Classifier: Development Status :: 3 - Alpha
Classifier: Intended Audience :: Developers
Classifier: License :: OSI Approved :: MIT License
Classifier: Programming Language :: Python :: 2
Classifier: Programming Language :: Python :: 3
Requires-Python: >=2.7
Requires-Dist: requests
Requires-Dist: pycryptodome
Provides-Extra: bs4
Requires-Dist: bs4 ; extra == 'bs4'
